hsfs/__init__.py
hsfs/version.py
hsfs-0.0.0.2.dist-info/METADATA
hsfs-0.0.0.2.dist-info/WHEEL
hsfs-0.0.0.2.dist-info/top_level.txt
hsfs-0.0.0.2.dist-info/RECORD
